linecache2/__init__.py
linecache2/tests/test_linecache.py
linecache2/tests/__init__.py
linecache2/tests/inspect_fodder2.py
linecache2/tests/mapping_tests.py
linecache2/tests/inspect_fodder.py
linecache2-0.0.1.dist-info/metadata.json
linecache2-0.0.1.dist-info/DESCRIPTION.rst
linecache2-0.0.1.dist-info/RECORD
linecache2-0.0.1.dist-info/top_level.txt
linecache2-0.0.1.dist-info/WHEEL
linecache2-0.0.1.dist-info/METADATA
linecache2-0.0.1.dist-info/pbr.json
